{
  "project_info": {
    "project_number": "356715979644",
    "firebase_url": "https://pakistan-solar-fefaa-default-rtdb.firebaseio.com",
    "project_id": "pakistan-solar-fefaa",
    "storage_bucket": "pakistan-solar-fefaa.appspot.com"
  },
  "client": [
    {
      "client_info": {
        "mobilesdk_app_id": "1:356715979644:android:3e3ae82bb4a1d56e303af9",
        "android_client_info": {
          "package_name": "com.example.pakistan_solar_market"
        }
      },
      "oauth_client": [],
      "api_key": [
        {
          "current_key": "AIzaSyDU72zI5ehShs3bcL2t6-wcX9l1F5YuJ90"
        }
      ],
      "services": {
        "appinvite_service": {
          "other_platform_oauth_client": []
        }
      }
    }
  ],
  "configuration_version": "1"
}